TVG/FreeTVG.py
TVG/Tutorial TVG.pdf
TVG/__init__.py
TVG/bible_reader/__init__.py
TVG/bible_reader/bible_creator.py
TVG/bible_reader/database_bible_tvg.py
TVG/bible_reader/layout_BR.py
TVG/bible_reader/.Bible/KJV.xml
TVG/structure/__init__.py
TVG/structure/frame_layouts.py
TVG/utility/RegMail.py
TVG/utility/__init__.py
TVG/utility/data_parse.py
TVG/utility/database_tvg.py
TVG/utility/mdh.py
freetvg_karjakak-3.7.5.dist-info/LICENSE
freetvg_karjakak-3.7.5.dist-info/METADATA
freetvg_karjakak-3.7.5.dist-info/WHEEL
freetvg_karjakak-3.7.5.dist-info/entry_points.txt
freetvg_karjakak-3.7.5.dist-info/top_level.txt
freetvg_karjakak-3.7.5.dist-info/RECORD
