Metadata-Version: 2.2
Name: FreeTVG-karjakak
Version: 3.7.5
Summary: Tree View Gui for outline treeview note.
Author-email: karjakak <kakkarja.github@gmail.com>
License: MIT License
Project-URL: Homepage, https://github.com/kakkarja/FreeTVG#latest-notice
Keywords: TreeViewGui,TreeView Note,Note,MarkDown,Calculate Note
Classifier: Environment :: Win32 (MS Windows)
Classifier: Environment :: MacOS X
Classifier: Intended Audience :: End Users/Desktop
Classifier: Topic :: Text Editors :: Text Processing
Classifier: Programming Language :: Python :: 3.10
Classifier: License :: OSI Approved :: MIT License
Requires-Python: >=3.10
License-File: LICENSE
Requires-Dist: markdown>=3.3.4
Requires-Dist: pymdown-extensions>=9.0
Requires-Dist: treeview-karjakak>=1.8.1
Requires-Dist: excptr-karjakak>=0.1.0
Requires-Dist: demoji>=1.1.0
Requires-Dist: tomlkit>=0.11.6
Requires-Dist: darkdetect>=0.8.0
Requires-Dist: pdfkit>=1.0.0
Requires-Dist: addon_tvg-karjakak>=0.2.3
Requires-Dist: sqlmodel>=0.0.8
Requires-Dist: xmltodict>=0.13.0
